gml/__init__.py
gml/compile.py
gimbal_ai-0.0.1.dist-info/METADATA
gimbal_ai-0.0.1.dist-info/WHEEL
gimbal_ai-0.0.1.dist-info/top_level.txt
gimbal_ai-0.0.1.dist-info/RECORD
